slickcsv/__init__.py
slickcsv/client.py
slickcsv-0.0.3.dist-info/METADATA
slickcsv-0.0.3.dist-info/WHEEL
slickcsv-0.0.3.dist-info/top_level.txt
slickcsv-0.0.3.dist-info/RECORD
