Metadata-Version: 2.1
Name: slickcsv
Version: 0.0.3
Summary: Python client for slick-csv server
Author-email: "J. Hoffman" <johnmarianhoffman@gmail.com>
Project-URL: Homepage, https://gitlab.com/hoffman-lab/experimental-code/slick-csv
Project-URL: Bug Tracker, https://gitlab.com/hoffman-lab/experimental-code/slick-csv/issues
Classifier: Programming Language :: Python :: 3
Classifier: License :: OSI Approved :: BSD License
Classifier: Operating System :: OS Independent
Requires-Python: >=3.8
Requires-Dist: requests
